{"name": "Torch-npu",
    "version":"2.1.0.post6",
    "default":false,
    "framework_whl": [
        {"system":"linux_aarch64",
            "whl":[
                {
                    "filename":"torch-2.1.0-cp38-cp38-manylinux_2_17_aarch64.manylinux2014_aarch64.whl",
                    "url":"https://ascend-repo.obs.cn-east-2.myhuaweicloud.com/MindX/OpenSource/python/packages/5.0.0/torch-2.1.0-cp38-cp38-manylinux_2_17_aarch64.manylinux2014_aarch64.whl",
                    "dest":"pylibs/python3.8",
                    "python":"cp38",
                    "sha256":"761822761fffaa1c18a62c5deb13abaa780862577d3eadc428f1daa632536905"
                },
                {
                    "filename":"torch_npu-2.1.0.post6-cp38-cp38-manylinux_2_17_aarch64.manylinux2014_aarch64.whl",
                    "url":"https://ascend-repo.obs.cn-east-2.myhuaweicloud.com/MindX/OpenSource/python/packages/torch_npu-2.1.0.post6-cp38-cp38-manylinux_2_17_aarch64.manylinux2014_aarch64.whl",
                    "dest":"pylibs/python3.8",
                    "python":"cp38",
                    "sha256":"740981adf18b437d3f6af9be310237c0d2609f19948f4f2342f4d36c9578b845"
                },
                {
                    "filename":"torch-2.1.0-cp39-cp39-manylinux_2_17_aarch64.manylinux2014_aarch64.whl",
                    "url":"https://ascend-repo.obs.cn-east-2.myhuaweicloud.com/MindX/OpenSource/python/packages/5.0.0/torch-2.1.0-cp39-cp39-manylinux_2_17_aarch64.manylinux2014_aarch64.whl",
                    "dest":"pylibs/python3.9",
                    "python":"cp39",
                    "sha256":"de7d63c6ecece118684415a3dbd4805af4a4c1ee1490cccf7405d8c240a481b4"
                },
                {
                    "filename":"torch_npu-2.1.0.post6-cp39-cp39-manylinux_2_17_aarch64.manylinux2014_aarch64.whl",
                    "url":"https://ascend-repo.obs.cn-east-2.myhuaweicloud.com/MindX/OpenSource/python/packages/torch_npu-2.1.0.post6-cp39-cp39-manylinux_2_17_aarch64.manylinux2014_aarch64.whl",
                    "dest":"pylibs/python3.9",
                    "python":"cp39",
                    "sha256":"2b02df1c0f4e99ebfb8cd57d33538b217b943a7e7fae575e050c49be9c775b06"
                },
                {
                    "filename":"torch-2.1.0-cp310-cp310-manylinux_2_17_aarch64.manylinux2014_aarch64.whl",
                    "url":"https://ascend-repo.obs.cn-east-2.myhuaweicloud.com/MindX/OpenSource/python/packages/5.0.0/torch-2.1.0-cp310-cp310-manylinux_2_17_aarch64.manylinux2014_aarch64.whl",
                    "dest":"pylibs/python3.10",
                    "python":"cp310",
                    "sha256":"a04a0296d47f28960f51c18c5489a8c3472f624ec3b5bcc8e2096314df8c3342"
                },
                {
                    "filename":"torch_npu-2.1.0.post6-cp310-cp310-manylinux_2_17_aarch64.manylinux2014_aarch64.whl",
                    "url":"https://ascend-repo.obs.cn-east-2.myhuaweicloud.com/MindX/OpenSource/python/packages/torch_npu-2.1.0.post6-cp310-cp310-manylinux_2_17_aarch64.manylinux2014_aarch64.whl",
                    "dest":"pylibs/python3.10",
                    "python":"cp310",
                    "sha256":"a9b9e567445a6562e87d8b6d144fc3007954504c3f4bbdcf93b2e75737ec27ee"
                }
            ]
        },
        {"system":"linux_x86_64",
            "whl":[
                {
                    "filename":"torch-2.1.0+cpu-cp38-cp38-linux_x86_64.whl",
                    "url":"https://ascend-repo.obs.cn-east-2.myhuaweicloud.com/MindX/OpenSource/python/packages/5.0.0/torch-2.1.0%2Bcpu-cp38-cp38-linux_x86_64.whl",
                    "dest":"pylibs/python3.8",
                    "python":"cp38",
                    "sha256":"9e5cfd931a65b38d222755a45dabb53b836be31bc620532bc66fee77e3ff67dc"
                },
                {
                    "filename":"torch_npu-2.1.0.post6-cp38-cp38-manylinux_2_17_x86_64.manylinux2014_x86_64.whl",
                    "url":"https://ascend-repo.obs.cn-east-2.myhuaweicloud.com/MindX/OpenSource/python/packages/torch_npu-2.1.0.post6-cp38-cp38-manylinux_2_17_x86_64.manylinux2014_x86_64.whl",
                    "dest":"pylibs/python3.8",
                    "python":"cp38",
                    "sha256":"e8d95354012c1c248db1b1de51d4611b50ee4890080617a73c0e673dab04c201"
                },
                {
                    "filename":"torch-2.1.0+cpu-cp39-cp39-linux_x86_64.whl",
                    "url":"https://ascend-repo.obs.cn-east-2.myhuaweicloud.com/MindX/OpenSource/python/packages/5.0.0/torch-2.1.0%2Bcpu-cp39-cp39-linux_x86_64.whl",
                    "dest":"pylibs/python3.9",
                    "python":"cp39",
                    "sha256":"86cc28df491fa84738affe752f9870791026565342f69e4ab63e5b935f00a495"
                },
                {
                    "filename":"torch_npu-2.1.0.post6-cp39-cp39-manylinux_2_17_x86_64.manylinux2014_x86_64.whl",
                    "url":"https://ascend-repo.obs.cn-east-2.myhuaweicloud.com/MindX/OpenSource/python/packages/torch_npu-2.1.0.post6-cp39-cp39-manylinux_2_17_x86_64.manylinux2014_x86_64.whl",
                    "dest":"pylibs/python3.9",
                    "python":"cp39",
                    "sha256":"4396b1d2b1fee94a63c3a10ac0a292e7c4cbf521a50df2df2d28636a40029b85"
                },
                {
                    "filename":"torch-2.1.0+cpu-cp310-cp310-linux_x86_64.whl",
                    "url":"https://ascend-repo.obs.cn-east-2.myhuaweicloud.com/MindX/OpenSource/python/packages/5.0.0/torch-2.1.0%2Bcpu-cp310-cp310-linux_x86_64.whl",
                    "dest":"pylibs/python3.10",
                    "python":"cp310",
                    "sha256":"5077921fc2b54e69a534f3a9c0b98493c79a5547c49d46f5e77e42da3610e011"
                },
                {
                    "filename":"torch_npu-2.1.0.post6-cp310-cp310-manylinux_2_17_x86_64.manylinux2014_x86_64.whl",
                    "url":"https://ascend-repo.obs.cn-east-2.myhuaweicloud.com/MindX/OpenSource/python/packages/torch_npu-2.1.0.post6-cp310-cp310-manylinux_2_17_x86_64.manylinux2014_x86_64.whl",
                    "dest":"pylibs/python3.10",
                    "python":"cp310",
                    "sha256":"5f3e94a1b03803e82eb414356e48712078af26a9694df112545afbc171c527ab"
                }
            ]
        }
    ]
}